kamodo_ccmc/__init__.py
kamodo_ccmc/flythrough/SF_output.py
kamodo_ccmc/flythrough/SF_utilities.py
kamodo_ccmc/flythrough/SatelliteFlythrough.py
kamodo_ccmc/flythrough/__init__.py
kamodo_ccmc/flythrough/model_wrapper.py
kamodo_ccmc/flythrough/plots.py
kamodo_ccmc/flythrough/utils.py
kamodo_ccmc/readers/__init__.py
kamodo_ccmc/readers/adelphi_4D.py
kamodo_ccmc/readers/adelphi_tocdf.py
kamodo_ccmc/readers/amgeo_4D.py
kamodo_ccmc/readers/ctipe_4D.py
kamodo_ccmc/readers/ctipe_tocdf.py
kamodo_ccmc/readers/dtm_4D.py
kamodo_ccmc/readers/gameragm_4D.py
kamodo_ccmc/readers/gameragm_grids.py
kamodo_ccmc/readers/gameragm_model_custom.py
kamodo_ccmc/readers/gitm_4Dcdf.py
kamodo_ccmc/readers/gitm_tocdf.py
kamodo_ccmc/readers/hapi.py
kamodo_ccmc/readers/iri_4D.py
kamodo_ccmc/readers/model_custom.py
kamodo_ccmc/readers/openggcm_gm_4Dcdf.py
kamodo_ccmc/readers/openggcm_gm_tocdf.py
kamodo_ccmc/readers/reader_utilities.py
kamodo_ccmc/readers/sat_extractions.py
kamodo_ccmc/readers/superdarn_rename.py
kamodo_ccmc/readers/superdarn_tocdf.py
kamodo_ccmc/readers/superdarnequ_4D.py
kamodo_ccmc/readers/superdarnequ_interp.py
kamodo_ccmc/readers/superdarnuni_4D.py
kamodo_ccmc/readers/swmf_gm_octree.py
kamodo_ccmc/readers/swmfgm_4D.py
kamodo_ccmc/readers/swmfie_4Dcdf.py
kamodo_ccmc/readers/swmfie_tocdf.py
kamodo_ccmc/readers/tiegcm_4D.py
kamodo_ccmc/readers/tiegcm_tocdf.py
kamodo_ccmc/readers/waccmx_4D.py
kamodo_ccmc/readers/waccmx_tocdf.py
kamodo_ccmc/readers/wamipe_4D.py
kamodo_ccmc/readers/wamipe_tocdf.py
kamodo_ccmc/readers/weimer_4D.py
kamodo_ccmc/readers/weimer_tocdf.py
kamodo_ccmc/readers/OCTREE_BLOCK_GRID/interpolate_amrdata_extension_build.py
kamodo_ccmc/readers/OpenGGCM/openggcm_gm_tocdf.py
kamodo_ccmc/tools/__init__.py
kamodo_ccmc/tools/constellation.py
kamodo_ccmc/tools/functionalize.py
kamodo_ccmc/tools/functionalize_hapi.py
kamodo_ccmc/tools/plotfunctions.py
kamodo_ccmc/tools/shoreline.py
kamodo_ccmc-23.3.1.dist-info/LICENSE
kamodo_ccmc-23.3.1.dist-info/METADATA
kamodo_ccmc-23.3.1.dist-info/WHEEL
kamodo_ccmc-23.3.1.dist-info/top_level.txt
kamodo_ccmc-23.3.1.dist-info/RECORD
