Metadata-Version: 2.1
Name: kamodo-ccmc
Version: 23.3.1
Summary: A functional api for scientific data
Home-page: https://github.com/nasa/Kamodo
Author: Darren De Zeeuw
Author-email: darren.dezeeuw@nasa.gov
License: NASA OPEN SOURCE AGREEMENT VERSION 1.3
Project-URL: Repository, https://github.com/nasa/Kamodo
Project-URL: Documentation, https://nasa.github.io/Kamodo
Classifier: Programming Language :: Python :: 3.7
Classifier: Operating System :: OS Independent
Classifier: License :: OSI Approved
Requires-Python: >=3.7
License-File: LICENSE
Requires-Dist: kamodo (==22.5.0)
Requires-Dist: numpy
Requires-Dist: netCDF4
Requires-Dist: cdflib
Requires-Dist: astropy
Requires-Dist: ipython
Requires-Dist: jupyter
Requires-Dist: h5py
Requires-Dist: sgp4
Requires-Dist: hapiclient
Requires-Dist: spacepy
